syhep/__init__.py
syhep/extras.py
syhep-0.0.1.dist-info/METADATA
syhep-0.0.1.dist-info/WHEEL
syhep-0.0.1.dist-info/licenses/LICENSE
syhep-0.0.1.dist-info/RECORD
