Metadata-Version: 2.4
Name: syhep
Version: 0.0.1
Summary: Symbolic calculations for High Energy Particle physics using python and SymPy
Project-URL: Homepage, https://github.com/mardsouza/syhep
Project-URL: Issues, https://github.com/mardsouza/syhep/issues
Author-email: Marcio de Souza <msmateusjr@gmail.com>
License-Expression: MIT
License-File: LICENSE
Classifier: Operating System :: OS Independent
Classifier: Programming Language :: Python :: 3
Requires-Python: >=3.9
